VulnHeist/Nmap_scan.py
VulnHeist/VulnHeist.py
VulnHeist/__init__.py
VulnHeist/exploit_functions.py
VulnHeist/main.py
VulnHeist-0.0.1.dist-info/LICENSE
VulnHeist-0.0.1.dist-info/METADATA
VulnHeist-0.0.1.dist-info/WHEEL
VulnHeist-0.0.1.dist-info/entry_points.txt
VulnHeist-0.0.1.dist-info/top_level.txt
VulnHeist-0.0.1.dist-info/RECORD
