Metadata-Version: 2.1
Name: VulnHeist
Version: 0.0.1
Summary: Automated Penetration Testing Suite leveraging Nmap and Metasploit Framework.
Home-page: https://github.com/Organisation-404/VulnHeist
Author: Team VulnHeist
Author-email: vulnheist@gmail.com
Project-URL: Bug Reports, https://github.com/Organisation-404/VulnHeist/issues
Project-URL: Source, https://github.com/Organisation-404/VulnHeist
Classifier: Programming Language :: Python :: 3
Classifier: License :: OSI Approved :: BSD License
Classifier: Operating System :: OS Independent
Classifier: Topic :: Security
Requires-Python: >=3.6
License-File: LICENSE
Requires-Dist: art
Requires-Dist: colorama
Requires-Dist: matplotlib
Requires-Dist: pyfiglet
Requires-Dist: pymetasploit3
Requires-Dist: python-libnmap
Requires-Dist: rich
